src/__init__.py
src/cli.py
src/exceptions.py
mullvad_cli_theheretic_0-0.1.0.dist-info/METADATA
mullvad_cli_theheretic_0-0.1.0.dist-info/WHEEL
mullvad_cli_theheretic_0-0.1.0.dist-info/licenses/LICENSE
mullvad_cli_theheretic_0-0.1.0.dist-info/RECORD
